qwergpt/__init__.py
qwergpt/document.py
qwergpt/evaluator.py
qwergpt/graph.py
qwergpt/logs.py
qwergpt/prompt.py
qwergpt/schema.py
qwergpt/solution_space.py
qwergpt/utils.py
qwergpt/bot/buffer_manager.py
qwergpt/bot/distiller.py
qwergpt/bot/retriever.py
qwergpt/bot/schema.py
qwergpt/embedders/__init__.py
qwergpt/embedders/base.py
qwergpt/embedders/ollama.py
qwergpt/embedders/sentence_transformer.py
qwergpt/embedders/zhipu.py
qwergpt/llms/__init__.py
qwergpt/llms/base.py
qwergpt/llms/deepseek.py
qwergpt/llms/errors.py
qwergpt/llms/ollama.py
qwergpt/llms/openai.py
qwergpt/llms/token_counter.py
qwergpt/llms/tonyi.py
qwergpt/llms/zhipu.py
qwergpt/pipelines/__init__.py
qwergpt/pipelines/base.py
qwergpt/pipelines/server.py
qwergpt/retrievers/__init__.py
qwergpt/retrievers/base.py
qwergpt/roles/__init__.py
qwergpt/roles/coder.py
qwergpt/roles/planner.py
qwergpt/roles/reviewer.py
qwergpt/roles/rewriter.py
qwergpt/stores/__init__.py
qwergpt/stores/base.py
qwergpt/stores/faiss.py
qwergpt/stores/milvus.py
qwergpt-0.1.2.dist-info/METADATA
qwergpt-0.1.2.dist-info/WHEEL
qwergpt-0.1.2.dist-info/licenses/LICENSE
qwergpt-0.1.2.dist-info/RECORD
